src/Sudoku_Solver/__init__.py
src/Sudoku_Solver/sudokusolver.py
automaticsudokusolver-0.0.1.dist-info/METADATA
automaticsudokusolver-0.0.1.dist-info/WHEEL
automaticsudokusolver-0.0.1.dist-info/licenses/LICENSE
automaticsudokusolver-0.0.1.dist-info/RECORD
