Metadata-Version: 2.1
Name: AutomaticSudokuSolver
Version: 0.0.1
Summary: A sudoku solver
Project-URL: Homepage, https://github.com/Mr-Piggy/Sudoku_Solver
Project-URL: Bug Tracker, https://github.com/Mr-Piggy/Sudoku_Solver/issues
Author-email: Sam <samstuff@samstuff.top>
License-File: LICENSE
Classifier: License :: OSI Approved :: MIT License
Classifier: Operating System :: OS Independent
Classifier: Programming Language :: Python :: 3
Requires-Python: >=3.7
